Metadata-Version: 2.1
Name: torch-frame
Version: 1.7.5
Summary: 用于深度学习快速实现代码的框架
Home-page: https://github.com/darknli/Pytorch-Frame/tree/main/torch_frame
Author: Darkn Lxs
Author-email: 1187220556@qq.com
License: UNKNOWN
Platform: UNKNOWN
Classifier: Programming Language :: Python :: 3
Classifier: License :: OSI Approved :: MIT License
Classifier: Operating System :: OS Independent
Requires-Python: >=3.6
Requires-Dist: termcolor
Requires-Dist: numpy (>=1.17)
Requires-Dist: opencv-python
Requires-Dist: tabulate
Requires-Dist: torch
Requires-Dist: transformers (>=4.25.1)
Requires-Dist: accelerate (>=0.16.0)
Requires-Dist: diffusers
Requires-Dist: pyyaml
Requires-Dist: tqdm
